setup.py
jadi/__init__.py
jadi/common.py
jadi/jadi.py
jadi.egg-info/PKG-INFO
jadi.egg-info/SOURCES.txt
jadi.egg-info/dependency_links.txt
jadi.egg-info/top_level.txt