Metadata-Version: 1.0
Name: jadi
Version: 1.0.2
Summary: Minimalistic IoC for Python
Home-page: https://github.com/ajenti/jadi
Author: Eugeny Pankov
Author-email: e@ajenti.org
License: UNKNOWN
Platform: UNKNOWN
